sparseregression/__init__.py
sparseregression/linear.py
sparseregression-0.0.1.dist-info/LICENSE.md
sparseregression-0.0.1.dist-info/METADATA
sparseregression-0.0.1.dist-info/WHEEL
sparseregression-0.0.1.dist-info/top_level.txt
sparseregression-0.0.1.dist-info/RECORD
