Metadata-Version: 2.1
Name: sparseregression
Version: 0.0.1
Summary: Sparse Regression
Home-page: https://github.com/ezuccarelli/sparseregression
Author: Eugenio Zuccarelli
Author-email: ezucca@mit.edu
License: UNKNOWN
Platform: UNKNOWN
Classifier: Programming Language :: Python :: 3
Classifier: License :: OSI Approved :: MIT License
Classifier: Operating System :: OS Independent
Requires-Python: >=3.6
